setup.py
bwrc_discovery_client.egg-info/PKG-INFO
bwrc_discovery_client.egg-info/SOURCES.txt
bwrc_discovery_client.egg-info/dependency_links.txt
bwrc_discovery_client.egg-info/requires.txt
bwrc_discovery_client.egg-info/top_level.txt
discovery_client/__init__.py
discovery_client/gradient_descent.py
discovery_client/user.py
discovery_client/errors/__init__.py
discovery_client/mock/__init__.py